streamlit_weather_widget/__init__.py
streamlit_weather_widget/frontend/build/asset-manifest.json
streamlit_weather_widget/frontend/build/bootstrap.min.css
streamlit_weather_widget/frontend/build/index.html
streamlit_weather_widget/frontend/build/precache-manifest.d9f32ea667f1ef3a8fa668a892be7191.js
streamlit_weather_widget/frontend/build/service-worker.js
streamlit_weather_widget/frontend/build/static/js/2.16706806.chunk.js
streamlit_weather_widget/frontend/build/static/js/2.16706806.chunk.js.LICENSE.txt
streamlit_weather_widget/frontend/build/static/js/2.16706806.chunk.js.map
streamlit_weather_widget/frontend/build/static/js/main.ef090707.chunk.js
streamlit_weather_widget/frontend/build/static/js/main.ef090707.chunk.js.map
streamlit_weather_widget/frontend/build/static/js/runtime-main.11ec9aca.js
streamlit_weather_widget/frontend/build/static/js/runtime-main.11ec9aca.js.map
streamlit_weather_widget-0.0.3.dist-info/LICENSE
streamlit_weather_widget-0.0.3.dist-info/METADATA
streamlit_weather_widget-0.0.3.dist-info/WHEEL
streamlit_weather_widget-0.0.3.dist-info/top_level.txt
streamlit_weather_widget-0.0.3.dist-info/RECORD
