Metadata-Version: 2.1
Name: streamlit-weather-widget
Version: 0.0.3
Summary: A component loading forecast data from OpenWeather and uses react-open-weather React component
Home-page: UNKNOWN
Author: ateeb
Author-email: 
License: UNKNOWN
Platform: UNKNOWN
Requires-Python: >=3.7
Requires-Dist: streamlit (>=0.63)
